tktermwidget/__init__.py
tktermwidget/style.py
tktermwidget/tkterm.py
tktermwidget-0.0.4.dist-info/LICENSE
tktermwidget-0.0.4.dist-info/METADATA
tktermwidget-0.0.4.dist-info/WHEEL
tktermwidget-0.0.4.dist-info/top_level.txt
tktermwidget-0.0.4.dist-info/RECORD
