Metadata-Version: 2.1
Name: tktermwidget
Version: 0.0.4
Summary: A terminal emulator for Tkinter
Home-page: https://github.com/littlewhitecloud/TkTerminal
Author: littlewhitecloud
License-File: LICENSE
